{
    "Joining_date": "2023-01-10",
    "addressdetails": {
        "address_line1": "No.54 munni Gowda Garden",
        "address_line2": "Neelasandra",
        "address_line3": "Neelasandra",
        "address_type": "Permanent",
        "country": 1,
        "county": "Bangalore",
        "created_at": "2023-01-27T05:49:02.000000Z",
        "created_by": null,
        "deleted": null,
        "emp_id": 6,
        "id": 1,
        "modifiable": null,
        "postcode": "560047",
        "state": 1,
        "status": null,
        "updated_at": "2023-01-27T05:49:02.000000Z",
        "updated_by": null
    },
    "api_token": null,
    "attribute1": null,
    "attribute2": null,
    "attribute3": null,
    "attribute4": null,
    "attribute5": null,
    "blood_group": 121,
    "bloodgrouplookupdetails": {
        "application": null,
        "created_at": null,
        "created_by": null,
        "default_status": null,
        "description": null,
        "from_date": null,
        "icon": "",
        "id": 121,
        "longname": "A+",
        "parent_id": 120,
        "seq": 1,
        "shortname": "A+",
        "slug": "a",
        "status": 1,
        "to_date": null,
        "type": null,
        "updated_at": null,
        "updated_by": null
    },
    "caste": null,
    "caste_id": null,
    "contactdetails": {
        "attribute1": null,
        "attribute2": null,
        "attribute3": null,
        "attribute4": null,
        "attribute5": null,
        "contact_id": "sabierhussain12@gmail.com",
        "created_at": "2023-01-27T05:49:02.000000Z",
        "created_by": null,
        "deleted": null,
        "emp_id": 6,
        "id": 1,
        "modifiable": null,
        "primary": null,
        "source": null,
        "status": null,
        "type_id": 106,
        "updated_at": "2023-01-27T05:49:02.000000Z",
        "updated_by": null
    },
    "created_at": "2023-01-24T12:29:56.000000Z",
    "created_by": null,
    "date_of_exit_int_flag": null,
    "date_of_exit_interview": null,
    "date_of_resignation": null,
    "date_of_settlement": null,
    "deleted": null,
    "designation_id": 56,
    "designationlookupdetails": {
        "application": null,
        "created_at": null,
        "created_by": null,
        "default_status": null,
        "description": null,
        "from_date": null,
        "icon": "",
        "id": 56,
        "longname": "Software Engineer - Trainee",
        "parent_id": 55,
        "seq": 1,
        "shortname": "Software Engineer - Trainee",
        "slug": "software-engineer",
        "status": 1,
        "to_date": null,
        "type": null,
        "updated_at": null,
        "updated_by": null
    },
    "disability": null,
    "division_id": null,
    "dob": null,
    "driver_status": "Y",
    "effective_date": null,
    "emp_education_details": [
        {
            "attribute1": null,
            "attribute2": null,
            "attribute3": null,
            "attribute4": null,
            "attribute5": null,
            "class_obtained": 140,
            "comments": null,
            "created_at": "2023-01-27T05:20:07.000000Z",
            "created_by": 1,
            "deleted": null,
            "educationprogramtype": [Object
            ],
            "emp_id": 6,
            "end_date": null,
            "enrolment_no": "080238566",
            "grade": null,
            "id": 1,
            "institute_name": "BHS",
            "modifiable": null,
            "program": 112,
            "source": null,
            "start_date": null,
            "status": null,
            "subject_major": "SSLC",
            "type_id": 116,
            "university_name": "Karnataka Secondary Education Examination Board",
            "updated_at": "2023-01-27T05:20:07.000000Z",
            "updated_by": null,
            "year_of_enrolment": "2012-04",
            "year_of_passing": "2013-03"
        },
        {
            "attribute1": null,
            "attribute2": null,
            "attribute3": null,
            "attribute4": null,
            "attribute5": null,
            "class_obtained": 140,
            "comments": null,
            "created_at": "2023-01-27T05:21:27.000000Z",
            "created_by": 1,
            "deleted": null,
            "educationprogramtype": [Object
            ],
            "emp_id": 6,
            "end_date": null,
            "enrolment_no": "20157086",
            "grade": null,
            "id": 2,
            "institute_name": "SJIC PUC",
            "modifiable": null,
            "program": 112,
            "source": null,
            "start_date": null,
            "status": null,
            "subject_major": "PCMB",
            "type_id": 117,
            "university_name": "Department of Pre-University Education",
            "updated_at": "2023-01-27T05:21:27.000000Z",
            "updated_by": null,
            "year_of_enrolment": "2013-04",
            "year_of_passing": "2015-05"
        },
        {
            "attribute1": null,
            "attribute2": null,
            "attribute3": null,
            "attribute4": null,
            "attribute5": null,
            "class_obtained": 140,
            "comments": null,
            "created_at": "2023-01-27T05:22:51.000000Z",
            "created_by": 1,
            "deleted": null,
            "educationprogramtype": [Object
            ],
            "emp_id": 6,
            "end_date": null,
            "enrolment_no": "157086",
            "grade": null,
            "id": 3,
            "institute_name": "AIIS",
            "modifiable": null,
            "program": 112,
            "source": null,
            "start_date": null,
            "status": null,
            "subject_major": "Bachelor of Computer Application",
            "type_id": 118,
            "university_name": "Bangalore University",
            "updated_at": "2023-01-27T05:22:51.000000Z",
            "updated_by": null,
            "year_of_enrolment": "2015-06",
            "year_of_passing": "2018-08"
        }
    ],
    "emp_job_history": [
        {
            "attribute1": null,
            "attribute2": null,
            "attribute3": null,
            "attribute4": null,
            "attribute5": null,
            "comments": null,
            "created_at": "2023-01-27T05:33:32.000000Z",
            "created_by": 1,
            "ctc": null,
            "deleted": null,
            "designation": "Software Engineer Trainee",
            "designation_time_of_join": null,
            "emp_id": 6,
            "emp_status": 92,
            "employer_contact": null,
            "employer_email": "enquiry@agileidc.com",
            "employer_name": "Agilets Private Limited",
            "employer_phone": "7400700700",
            "employer_website": "https://www.agileidc.com",
            "end_date": "2022-02-01",
            "id": 1,
            "job_status": null,
            "job_status_id": null,
            "key_skills": null,
            "last_reporting_manager": "Dr.Raghu",
            "modifiable": null,
            "reason_for_leaving": "Converted to permanent employee",
            "source": null,
            "start_date": "2021-10-10",
            "status": null,
            "type_id": 94,
            "updated_at": "2023-01-27T05:33:32.000000Z",
            "updated_by": null
        }
    ],
    "emp_no_gen_type": null,
    "emp_skill_details": [],
    "emp_status": 91,
    "emp_type": 95,
    "empno": "AG5",
    "emptypelookupdetails": {
        "application": null,
        "created_at": null,
        "created_by": null,
        "default_status": null,
        "description": null,
        "from_date": null,
        "icon": "",
        "id": 95,
        "longname": "Full Time",
        "parent_id": 93,
        "seq": 2,
        "shortname": "Full Time",
        "slug": "full_time",
        "status": 1,
        "to_date": null,
        "type": null,
        "updated_at": null,
        "updated_by": null
    },
    "enable_exit_button": null,
    "enable_exit_interview_flag": null,
    "end_of_probation": null,
    "esic": null,
    "exit_int_remarks": null,
    "family_details": [
        {
            "attribute1": null,
            "attribute2": null,
            "attribute3": null,
            "attribute4": null,
            "attribute5": null,
            "contactnumber": null,
            "created_at": "2023-01-27T05:23:45.000000Z",
            "created_by": null,
            "deleted": null,
            "dob": "1993-04-24",
            "emp_id": 6,
            "first_name": "Yass",
            "id": 1,
            "last_name": "Hussain",
            "modifiable": null,
            "nomination_percentage": null,
            "nominee": null,
            "occupation": null,
            "passport_number": null,
            "place_of_birth": null,
            "primary": null,
            "qualification": null,
            "source": null,
            "status": null,
            "type_id": 41,
            "updated_at": "2023-01-27T05:23:45.000000Z",
            "updated_by": null
        },
        {
            "attribute1": null,
            "attribute2": null,
            "attribute3": null,
            "attribute4": null,
            "attribute5": null,
            "contactnumber": null,
            "created_at": "2023-01-27T05:26:34.000000Z",
            "created_by": null,
            "deleted": null,
            "dob": "1967-01-01",
            "emp_id": 6,
            "first_name": "Zulekha",
            "id": 2,
            "last_name": "Begum",
            "modifiable": null,
            "nomination_percentage": null,
            "nominee": null,
            "occupation": null,
            "passport_number": null,
            "place_of_birth": null,
            "primary": null,
            "qualification": null,
            "source": null,
            "status": null,
            "type_id": 40,
            "updated_at": "2023-01-27T05:26:34.000000Z",
            "updated_by": null
        }
    ],
    "father_name": null,
    "filename": null,
    "firstname": "Shaik",
    "full_details": "Shaik  Hussain (shaika@agileidc.com)",
    "full_name": "Shaik  Hussain",
    "gender": "Male",
    "height": "175",
    "id": 6,
    "identity_mark": null,
    "lastname": "Hussain",
    "leave_calc_year_flag": null,
    "level_id": 1,
    "maritalstatus_id": 13,
    "martialstatuslookupdetails": {
        "application": null,
        "created_at": null,
        "created_by": null,
        "default_status": null,
        "description": null,
        "from_date": null,
        "icon": "",
        "id": 13,
        "longname": "Single",
        "parent_id": 12,
        "seq": 1,
        "shortname": "Single",
        "slug": "single",
        "status": 1,
        "to_date": null,
        "type": null,
        "updated_at": null,
        "updated_by": null
    },
    "middlename": "",
    "mimetype": null,
    "mode_of_transfer": null,
    "modifiable": null,
    "nationality_id": 83,
    "nationalitylookupdetails": {
        "application": null,
        "created_at": null,
        "created_by": null,
        "default_status": null,
        "description": null,
        "from_date": null,
        "icon": "",
        "id": 83,
        "longname": "Indian",
        "parent_id": 82,
        "seq": 1,
        "shortname": "Indian",
        "slug": "indian",
        "status": 1,
        "to_date": null,
        "type": null,
        "updated_at": null,
        "updated_by": null
    },
    "new_user_flag": null,
    "noc_comments": null,
    "office_ref_num": null,
    "old_empno": "AG5",
    "org_id": 1,
    "org_name": null,
    "passport_status": null,
    "personal_email": "shaik@gmail.com",
    "phone": null,
    "professional_summary": null,
    "profile_pic": null,
    "provident_fund": null,
    "region": null,
    "relieve_earned_leave_no": null,
    "relieving_date": null,
    "religion_id": 86,
    "resigning_reason": null,
    "role_id": null,
    "rolename": "",
    "salutation": "Mr",
    "settlement_amount": null,
    "settlement_doc": null,
    "settlement_filename": null,
    "settlement_mimetype": null,
    "site_id": 1,
    "slug": "shaik-hussain-2",
    "social_id": "1234567890",
    "source": null,
    "status": 1,
    "status_date": null,
    "title": null,
    "transfer_reference": null,
    "travel_status": null,
    "unique_account_no": null,
    "update_empno": null,
    "updated_at": "2023-01-27T05:06:28.000000Z",
    "updated_by": null,
    "user_level": null,
    "weight": "81"
}
